classifiedjson/__init__.py
classifiedjson/api.py
classifiedjson/constants.py
classifiedjson/encoder_interface.py
classifiedjson/factory.py
classifiedjson/hook_item.py
classifiedjson/kind_data.py
classifiedjson/kind_enum.py
classifiedjson/kind_serialization.py
classifiedjson/native_encoder.py
classifiedjson/standard_deserializer.py
classifiedjson/standard_serializer.py
classifiedjson/utils.py
classifiedjson/natives/array.py
classifiedjson/natives/bytes.py
classifiedjson/natives/dict.py
classifiedjson/natives/float_special.py
classifiedjson/standards/containers.py
classifiedjson/standards/custom_attribute.py
classifiedjson/standards/dataclass.py
classifiedjson/standards/datetime.py
classifiedjson/standards/enum.py
classifiedjson/standards/scalars.py
classifiedjson-1.1.0.dist-info/LICENSE
classifiedjson-1.1.0.dist-info/METADATA
classifiedjson-1.1.0.dist-info/WHEEL
classifiedjson-1.1.0.dist-info/top_level.txt
classifiedjson-1.1.0.dist-info/RECORD
