Metadata-Version: 2.1
Name: classifiedjson
Version: 1.1.0
Summary: Preserve types when dumping and loading data with JSON
Author-email: Jon Guerin <jg@shootingsoul.com>
Project-URL: Homepage, https://github.com/shootingsoul/classifiedjson
Project-URL: Bug Tracker, https://github.com/shootingsoul/classifiedjson/issues
Project-URL: Changelog, https://github.com/shootingsoul/classifiedjson/CHANGELOG.md
Project-URL: Source, https://github.com/shootingsoul/classifiedjson
Project-URL: Download, https://github.com/shootingsoul/classifiedjson/#files
Classifier: Development Status :: 3 - Alpha
Classifier: Programming Language :: Python :: 3
Classifier: Programming Language :: Python :: 3.8
Classifier: Programming Language :: Python :: 3.9
Classifier: Programming Language :: Python :: 3.10
Classifier: Programming Language :: Python :: 3.11
Classifier: Programming Language :: Python :: 3.12
Classifier: Operating System :: OS Independent
Classifier: Intended Audience :: Developers
Classifier: Intended Audience :: Information Technology
Classifier: Intended Audience :: System Administrators
Classifier: License :: OSI Approved :: MIT License
Classifier: Typing :: Typed
Classifier: Topic :: Software Development :: Libraries :: Python Modules
Requires-Python: >=3.8
License-File: LICENSE
